<?xml version="1.0" encoding="utf-8"?>
<intrinsics><projection><fu>1227.531545049066</fu><sigma_fu>1.377583358629115</sigma_fu><fv>1223.191127174513</fv><sigma_fv>1.353950967597793</sigma_fv><cu>628.5404541715689</cu><sigma_cu>1.055208368339841</sigma_cu><cv>502.5012720145764</cv><sigma_cv>0.9553735742395562</sigma_cv><ru>1280</ru><rv>960</rv><type>pinhole</type><distortion><k1>-0.3160877179434898</k1><sigma_k1>0.001155567856098239</sigma_k1><k2>0.1307793459097717</k2><sigma_k2>0.002530338839832882</sigma_k2><p1>0.0006876942680489816</p1><sigma_p1>0.0001427498105701529</sigma_p1><p2>-0.0003457772005868679</p2><sigma_p2>0.0001304889537393551</sigma_p2></distortion></projection><shutter><line-delay>0</line-delay></shutter><mask><mask-file/></mask></intrinsics>